{
    "Pizza": {
        "Prix": 6.00,
        "Recettes": {
            "Personnalisable": {
                "Base": [], 
                "Ingrédients": []
            },
            "Meat BBQ (poulet)": {
                "Base": [], 
                "Ingrédients": ["Mozzarella", "Oignons", "Poivrons", "Poulet", "Sauce BBQ"]
            },
            "Meat BBQ (lardon)": {
                "Base": [], 
                "Ingrédients": ["Mozzarella", "Oignons", "Poivrons", "Lardon", "Sauce BBQ"]
            },
            "Aïe Caramba (poulet)": {
                "Base": [], 
                "Ingrédients": ["Mozzarella", "Oignons", "Poivrons", "Haricots rouges", "Maïs","Poulet"]
            },
            "Aïe Caramba (lardon)": {
                "Base": [], 
                "Ingrédients": ["Mozzarella", "Oignons", "Poivrons", "Haricots rouges", "Maïs","Lardon"]
            },
            "Végé": {
                "Base": [], 
                "Ingrédients": ["Mozzarella", "Oignons", "Poivrons", "Champignons", "Olives noires", "Roquette"]
            }
        }
    },
    "Grillade": {
        "Prix": 5.00
    },
    "Frites": {
        "Prix": 2.50
    },
    "Salade composée": {
        "Prix": 4.00
    }
}